gridgym/__init__.py
gridgym/__version__.py
gridgym/envs/__init__.py
gridgym/envs/grid_env.py
gridgym/envs/off_reservation_env.py
gridgym/envs/scheduling_env.py
gridgym-0.2.0.dist-info/LICENSE
gridgym-0.2.0.dist-info/METADATA
gridgym-0.2.0.dist-info/WHEEL
gridgym-0.2.0.dist-info/top_level.txt
gridgym-0.2.0.dist-info/RECORD
